protoboiler/__init__.py
protoboiler-1.2.2.dist-info/LICENSE.md
protoboiler-1.2.2.dist-info/METADATA
protoboiler-1.2.2.dist-info/WHEEL
protoboiler-1.2.2.dist-info/entry_points.txt
protoboiler-1.2.2.dist-info/RECORD
