Metadata-Version: 2.1
Name: protoboiler
Version: 1.2.2
Summary: Protocol Buffers compiler plugin to quickly generate boilerplate code from your Google Protocol Buffer (proto) definitions.
Home-page: https://github.com/in4lio/protoboiler
License: MIT
Author: Vitaly Kravtsov
Author-email: in4lio@gmail.com
Requires-Python: >=3.11,<4.0
Classifier: License :: OSI Approved :: MIT License
Classifier: Programming Language :: Python :: 3
Classifier: Programming Language :: Python :: 3.11
Classifier: Programming Language :: Python :: 3.12
Requires-Dist: f-codec (>=0.1.1,<0.2.0)
Requires-Dist: protobuf (>=5.27.2,<6.0.0)
